README.md
setup.py
skydive_shell/__init__.py
skydive_shell/shell.py
skydive_shell/utils.py
skydive_shell.egg-info/PKG-INFO
skydive_shell.egg-info/SOURCES.txt
skydive_shell.egg-info/dependency_links.txt
skydive_shell.egg-info/entry_points.txt
skydive_shell.egg-info/requires.txt
skydive_shell.egg-info/top_level.txt