Metadata-Version: 1.0
Name: skydive-shell
Version: 0.3
Summary: An interactive Shell for Skydive
Home-page: https://github.com/nlewo/skydive-shell
Author: Antoine Eiche
Author-email: lewo@abesis.fr
License: UNKNOWN
Platform: UNKNOWN
